LICENSE.md
README.md
bio_embeddings_duongttr/__init__.py
bio_embeddings_duongttr/align/__init__.py
bio_embeddings_duongttr/align/deepblast.py
bio_embeddings_duongttr/align/mmseqs2.py
bio_embeddings_duongttr/align/pipeline.py
bio_embeddings_duongttr/bio_embeddings_schema.json
bio_embeddings_duongttr/embed/__init__.py
bio_embeddings_duongttr/embed/bepler_embedder.py
bio_embeddings_duongttr/embed/cpcprot_embedder.py
bio_embeddings_duongttr/embed/embedder_interfaces.py
bio_embeddings_duongttr/embed/esm_embedder.py
bio_embeddings_duongttr/embed/fasttext_embedder.py
bio_embeddings_duongttr/embed/glove_embedder.py
bio_embeddings_duongttr/embed/one_hot_encoding_embedder.py
bio_embeddings_duongttr/embed/pipeline.py
bio_embeddings_duongttr/embed/plus_rnn_embedder.py
bio_embeddings_duongttr/embed/prottrans_albert_bfd_embedder.py
bio_embeddings_duongttr/embed/prottrans_base_embedder.py
bio_embeddings_duongttr/embed/prottrans_bert_bfd_embedder.py
bio_embeddings_duongttr/embed/prottrans_t5_embedder.py
bio_embeddings_duongttr/embed/prottrans_xlnet_uniref100_embedder.py
bio_embeddings_duongttr/embed/seqvec_embedder.py
bio_embeddings_duongttr/embed/unirep_embedder.py
bio_embeddings_duongttr/embed/word2vec_embedder.py
bio_embeddings_duongttr/extract/__init__.py
bio_embeddings_duongttr/extract/annotations/__init__.py
bio_embeddings_duongttr/extract/annotations/binding_residues.py
bio_embeddings_duongttr/extract/annotations/conservation.py
bio_embeddings_duongttr/extract/annotations/disorder.py
bio_embeddings_duongttr/extract/annotations/location.py
bio_embeddings_duongttr/extract/annotations/membrane.py
bio_embeddings_duongttr/extract/annotations/membrane_residues.py
bio_embeddings_duongttr/extract/annotations/secondary_structure.py
bio_embeddings_duongttr/extract/basic/__init__.py
bio_embeddings_duongttr/extract/basic/annotation_inference_models.py
bio_embeddings_duongttr/extract/basic/basic_annotation_extractor.py
bio_embeddings_duongttr/extract/bindEmbed21/__init__.py
bio_embeddings_duongttr-0.2.3.dist-info/entry_points.txt
bio_embeddings_duongttr-0.2.3.dist-info/LICENSE.md
bio_embeddings_duongttr-0.2.3.dist-info/WHEEL
bio_embeddings_duongttr-0.2.3.dist-info/METADATA
bio_embeddings_duongttr-0.2.3.dist-info/RECORD
