Metadata-Version: 2.1
Name: bio-embeddings-duongttr
Version: 0.2.3
Summary: A pipeline for protein embedding generation and visualization
License: MIT
Author: Christian Dallago
Author-email: christian.dallago@tum.de
Maintainer: Rostlab
Maintainer-email: admin@rostlab.org
Requires-Python: >=3.8,<3.10
Classifier: Intended Audience :: Science/Research
Classifier: License :: OSI Approved :: MIT License
Classifier: Operating System :: OS Independent
Classifier: Programming Language :: Python :: 3
Classifier: Programming Language :: Python :: 3.7
Classifier: Programming Language :: Python :: 3.8
Classifier: Programming Language :: Python :: 3.9
Classifier: Topic :: Scientific/Engineering :: Bio-Informatics
Classifier: Topic :: Scientific/Engineering :: Visualization
Provides-Extra: all
Provides-Extra: bepler
Provides-Extra: cpcprot
Provides-Extra: deepblast
Provides-Extra: esm
Provides-Extra: plus
Provides-Extra: prottrans
Provides-Extra: seqvec
Provides-Extra: transformers
Provides-Extra: unirep
Provides-Extra: webserver
Requires-Dist: appdirs (>=1.4.4,<2.0.0)
Requires-Dist: atomicwrites (>=1.4.0,<2.0.0)
Requires-Dist: bio-embeddings-allennlp (==0.9.2); extra == "seqvec" or extra == "all"
Requires-Dist: bio-embeddings-bepler (==0.0.1); extra == "bepler" or extra == "all"
Requires-Dist: bio-embeddings-cpcprot (==0.0.1); extra == "cpcprot" or extra == "all"
Requires-Dist: bio-embeddings-deepblast (==0.1.0); extra == "deepblast" or extra == "all"
Requires-Dist: bio-embeddings-plus (==0.1.1); extra == "plus" or extra == "all"
Requires-Dist: bio-embeddings-tape-proteins (==0.5); extra == "cpcprot" or extra == "all"
Requires-Dist: biopython (>=1.79,<2.0)
Requires-Dist: celery (>=5.2.7,<6.0.0)
Requires-Dist: fair-esm (==2.0.0); extra == "esm" or extra == "all"
Requires-Dist: flask (>=2.1.2,<3.0.0); extra == "webserver"
Requires-Dist: flask-cors (>=3.0.10,<4.0.0)
Requires-Dist: fsspec (==0.8.5); extra == "deepblast"
Requires-Dist: gensim (>=4.2.0,<5.0.0)
Requires-Dist: gunicorn (>=20.1.0,<21.0.0)
Requires-Dist: h5py (>=3.7.0,<4.0.0)
Requires-Dist: humanize (>=4.1.0,<5.0.0)
Requires-Dist: importlib_metadata (>=4.11.4,<5.0.0)
Requires-Dist: jax-unirep (>=2.1.0,<3.0.0); extra == "unirep" or extra == "all"
Requires-Dist: jaxlib (>=0.3.10,<0.4.0); extra == "unirep"
Requires-Dist: lock (>=2018.3.25,<2019.0.0)
Requires-Dist: matplotlib (>=3.5.2,<4.0.0)
Requires-Dist: numpy (>=1.19.2,<2.0.0)
Requires-Dist: pandas (>=1.4.2,<2.0.0)
Requires-Dist: plotly (>=5.8.0,<6.0.0)
Requires-Dist: pymongo (>=4.1.1,<5.0.0); extra == "webserver"
Requires-Dist: python-slugify (>=6.1.2,<7.0.0)
Requires-Dist: pyyaml (==6.0)
Requires-Dist: ruamel.yaml (>=0.17.10,<0.18.0)
Requires-Dist: scikit-learn (>=1.1.1,<2.0.0)
Requires-Dist: scipy (>=1.8.1,<2.0.0)
Requires-Dist: sentencepiece (==0.1.96)
Requires-Dist: sentry-sdk[flask] (>=1.5.12,<2.0.0); extra == "webserver"
Requires-Dist: torch (>=1.8.0,<=1.10.0)
Requires-Dist: tqdm (>=4.64.0,<5.0.0)
Requires-Dist: transformers (>=4.19.2,<5.0.0); extra == "prottrans" or extra == "transformers" or extra == "all"
Requires-Dist: umap-learn (>=0.5.3,<0.6.0)
Requires-Dist: vespa-effect (>=1.0.0,<2.0.0); python_version >= "3.8" and python_version < "4.0"
Requires-Dist: werkzeug (==2.0.3)
Project-URL: homepage, https://visualize.protein.properties
Project-URL: issues, https://github.com/sacdallago/bio_embeddings/issues
Project-URL: repository, https://github.com/sacdallago/bio_embeddings
